[
    {
        "name": "Ajay",
        "phone_Number": "7736198405",
        "club": "Stallions",
    },
    {
        "name": "Anu",
        "phone_Number": "9745662513",
        "club": "Fighters ",
    },
    {
        "name": "Shaji",
        "phone_Number": "8086408908",
        "club": "Fighters ",
    },
    {
        "name": "SUBASH ",
        "phone_Number": "8089564748",
        "club": "NEW ROYAL",
    },
    {
        "name": "Kevin",
        "phone_Number": "9895919578",
        "club": "Srs",
        "\"\"": "9895919578"
    },
    {
        "name": "Sudheesh ",
        "phone_Number": "7902828812",
        "club": "Chunkzzz",
        "\"\"": "7902828812"
    },
    {
        "name": "Jaya Prakash",
        "phone_Number": "9633051783",
        "club": "Scorpion cc",
        "\"\"": "513794039540"
    },
    {
        "name": "Soorya.p",
        "phone_Number": "9037045641",
        "club": "New royals",
        "\"\"": "9037045641"
    },
    {
        "name": "Madhu M",
        "phone_Number": "9074054009",
        "club": "New Royals",
        "\"\"": "513725284960"
    },
    {
        "name": "Azar",
        "phone_Number": "8089818127",
        "club": "Bcc canalpirivu",
        "\"\"": "12345678"
    },
    {
        "name": "Vishnu",
        "phone_Number": "6282694916",
        "club": "Vattappara",
        "\"\"": "1234568"
    },
    {
        "name": "Ranjith",
        "phone_Number": "7994822612",
        "club": "Scorpions",
        "\"\"": "513869293027"
    },
    {
        "name": "Daison ",
        "phone_Number": "9544633806",
        "club": "Pkd boys ",
    },
    {
        "name": "Aneesh",
        "phone_Number": "7907786334",
        "club": "Nallur rising star",
    },
    {
        "name": "Sadhik kozhinjampara ",
        "phone_Number": "9496921828",
        "club": "Phoenix kozhinjampara",
    },
    {
        "name": "Arun ",
        "phone_Number": "7909236684",
        "club": "Stallions ",
    },
    {
        "name": "Thamil",
        "phone_Number": "9995655454",
        "club": "Blasters cc",
    },
    {
        "name": "Ruban",
        "phone_Number": "7510774769",
        "club": "Ekr cricketers ",
    },
    {
        "name": "Ismail ",
        "phone_Number": "9074312043",
        "club": "Scorpions ",
    },
    {
        "name": "Francis ",
        "phone_Number": "9946209762",
        "club": "Pkd boys",
    },
    {
        "name": "Manikandan.d",
        "phone_Number": "9074015886",
        "club": "FIGHTERS",
    },
    {
        "name": "Mathew ",
        "phone_Number": "6238172824",
        "club": "Stephen cc",
    },
    {
        "name": "Akhil ",
        "phone_Number": "6238541961",
        "club": "Dracarys ",
    },
    {
        "name": "Pradeep",
        "phone_Number": "9809332833",
        "club": "Fightrs",
    },
    {
        "name": "JERIN ",
        "phone_Number": "7012225381 ",
        "club": "Stallion ",
    },
    {
        "name": "Daniel",
        "phone_Number": "7025242361",
        "club": "Stallions ",
    },
    {
        "name": "Vishnu",
        "phone_Number": "7306042080",
        "club": "Phoenix",
    },
    {
        "name": "Paul ",
        "phone_Number": "8129036415",
        "club": "Speed boys ",
    },
    {
        "name": "Edit",
        "phone_Number": "6238161701",
        "club": "Jokerz",
    },
    {
        "name": "Mani jockerz ",
        "phone_Number": "7025839343 ",
        "club": "Jockerz ",
    },
    {
        "name": "Charly",
        "phone_Number": "7559937279",
        "club": "Ekr cricketers",
    },
    {
        "name": "Kiran ",
        "phone_Number": "9946250266",
        "club": "Stallions",
    },
    {
        "name": "Manu",
        "phone_Number": "9072118650",
        "club": "Jokerz",
    },
    {
        "name": "Manju",
        "phone_Number": "7356948017",
        "club": "Ekr Cricketers",
    },
    {
        "name": "Praveen",
        "phone_Number": "9526650092",
        "club": "Erumaikkaranoor ",
    },
    
    {
        "name": "Salman farish ",
        "phone_Number": "9074215058",
        "club": "Nallur rising star's ",
    },
    {
        "name": "ANDROS",
        "phone_Number": "9497312928",
        "club": "Nallur rising star",
    },
    {
        "name": "Akshay",
        "phone_Number": "8891163595",
        "club": "Bsa",
    },
    {
        "name": "Skuttan",
        "phone_Number": "7560969865",
        "club": "Bsa",
    },
    {
        "name": "Sruthish s",
        "phone_Number": "8590370524",
        "club": "Bsa",
    },
    {
        "name": "Rajesh",
        "phone_Number": "9809690208",
        "club": "KL BROTHERS",
    },
    {
        "name": "Abbas ",
        "phone_Number": "9995634599",
        "club": "Kl brother ",
    },
    {
        "name": "Kalai ",
        "phone_Number": "9562828301",
        "club": "Phoenix Kozhinjampara ",
    },
    {
        "name": "Agilesh ",
        "phone_Number": "9809200670",
        "club": "Phoenix ",
    },
    {
        "name": "Anees uv",
        "phone_Number": "8137007221",
        "club": "Walayar Champions "club" ",
    },
    {
        "name": "Bibinraj",
        "phone_Number": "9946497133",
        "club": "Kongampara ",
    },
    {
        "name": "Asharaf ",
        "phone_Number": "7708609308",
        "club": "Pheonix ",
    },
    {
        "name": "Jose",
        "phone_Number": "9656289774",
        "club": "Klcc",
    },
    {
        "name": "Albi",
        "phone_Number": "7907877289",
        "club": "Scorpions ",
    },
    {
        "name": "Kevin ",
        "phone_Number": "9207901704",
        "club": "Stallions lo",
    },
    {
        "name": "Jerom",
        "phone_Number": "9539680590",
        "club": "Blasters cc ",
    },
    {
        "name": "Staney",
        "phone_Number": "9074172452",
        "club": "Pkd boys",
    },
    {
        "name": "KATHIR",
        "phone_Number": "8075802086",
        "club": "KL.BROTHERS",
    },
    {
        "name": "Aji",
        "phone_Number": "7012816557",
        "club": "New Royals vattappara",
    },
    {
        "name": "Adhi",
        "phone_Number": "7736055641",
        "club": "New Royals vattappara",
    },
   
    {
        "name": "STANLY LEO V",
        "phone_Number": "8082202877",
        "club": "Stallions ",
    },
    {
        "name": "Ebin",
        "phone_Number": "7907978734",
        "club": "Pkd boys",
    },
    {
        "name": "Nithin ",
        "phone_Number": "9995391974",
        "club": "PKD BOYS",
    },
    {
        "name": "Reni",
        "phone_Number": "8848936996",
        "club": "Unbeatable titans",
    },
    {
        "name": "Midhush",
        "phone_Number": "9777104642",
        "club": "Devilzz",
    },
    {
        "name": "Naveen NS",
        "phone_Number": "8848209277",
        "club": "Phoenix",
    },
    {
        "name": "Dhanee",
        "phone_Number": "+918590188293",
        "club": "Fighters kozhinjamPara ",
    },
    {
        "name": "Jikson A",
        "phone_Number": "7012295719",
        "club": "Skyhawks ",
    },
    {
        "name": "Akash",
        "phone_Number": "8078908124",
        "club": "Phoenix ",
    },
    {
        "name": "Rassu",
        "phone_Number": "8547611432",
        "club": "Phoenix ",
    },
    {
        "name": "Kalai ",
        "phone_Number": "9562828301",
        "club": "Pheonix ",
    },
    {
        "name": "Appu",
        "phone_Number": "9074065050",
        "club": "Chandhapetta",
    },
    {
        "name": "Abbas",
        "phone_Number": "9495229471",
        "club": "Chellengers",
    },
    {
        "name": "Darry",
        "phone_Number": "7994919834",
        "club": "Pkd boys",
    },
    {
        "name": "Jekan",
        "phone_Number": "8848861653",
        "club": "Pkd boys",
    },
    {
        "name": "Lara ",
        "phone_Number": "8921188744",
        "club": "Nil",
    },
    {
        "name": "JENIFER ANTONY",
        "phone_Number": "9645257801",
        "club": "Stephen CC",
    },
    {
        "name": "Akhil",
        "phone_Number": "7306177117",
        "club": "Gmsc",
    },
    {
        "name": "Adhul",
        "phone_Number": "6238331003",
        "club": "Shine ",
    },
    {
        "name": "TINGU",
        "phone_Number": "8943711379",
        "club": "Phoenix",
    },
    {
        "name": "Babu",
        "phone_Number": "7907191682",
        "club": "King cobra ",
    },
    {
        "name": "Athul",
        "phone_Number": "8089677002",
        "club": "Chellengers ",
    },
    {
        "name": "Unni",
        "phone_Number": "9074812040",
        "club": "Chellengers ",
    },
    {
        "name": "Rahul",
        "phone_Number": "9995671287",
        "club": "Sorappara",
    },
    {
        "name": "Johnson",
        "phone_Number": "9037277961",
        "club": "Ekr cricketers ",
    },
    {
        "name": "Aswin ",
        "phone_Number": "9895854794",
        "club": "STALLIONS",
    },
    {
        "name": "Devit",
        "phone_Number": "7736198405",
        "club": "Ekr cricketers ",
    },
    {
        "name": "Akash",
        "phone_Number": "9809736361",
        "club": "Parisakkal",
    },
    {
        "name": "Viji",
        "phone_Number": "7994852078",
        "club": "Stallions",
    }
]